dronecan/__init__.py
dronecan/introspect.py
dronecan/node.py
dronecan/transport.py
dronecan/utility.py
dronecan/version.py
dronecan/app/__init__.py
dronecan/app/dynamic_node_id.py
dronecan/app/file_server.py
dronecan/app/log_message_monitor.py
dronecan/app/message_collector.py
dronecan/app/node_monitor.py
dronecan/driver/__init__.py
dronecan/driver/common.py
dronecan/driver/mavcan.py
dronecan/driver/mcast.py
dronecan/driver/python_can.py
dronecan/driver/slcan.py
dronecan/driver/socketcan.py
dronecan/driver/timestamp_estimator.py
dronecan/dsdl/__init__.py
dronecan/dsdl/common.py
dronecan/dsdl/parser.py
dronecan/dsdl/signature.py
dronecan/dsdl/type_limits.py
dronecan/dsdl_specs/ardupilot/equipment/power/20004.BatteryInfoAux.uavcan
dronecan/dsdl_specs/ardupilot/equipment/power/20010.BatteryContinuous.uavcan
dronecan/dsdl_specs/ardupilot/equipment/power/20011.BatteryPeriodic.uavcan
dronecan/dsdl_specs/ardupilot/equipment/power/20012.BatteryCells.uavcan
dronecan/dsdl_specs/ardupilot/equipment/proximity_sensor/21910.Proximity.uavcan
dronecan/dsdl_specs/ardupilot/equipment/trafficmonitor/20790.TrafficReport.uavcan
dronecan/dsdl_specs/ardupilot/gnss/20002.Heading.uavcan
dronecan/dsdl_specs/ardupilot/gnss/20003.Status.uavcan
dronecan/dsdl_specs/ardupilot/gnss/20005.MovingBaselineData.uavcan
dronecan/dsdl_specs/ardupilot/gnss/20006.RelPosHeading.uavcan
dronecan/dsdl_specs/ardupilot/indication/20000.SafetyState.uavcan
dronecan/dsdl_specs/ardupilot/indication/20001.Button.uavcan
dronecan/dsdl_specs/ardupilot/indication/20007.NotifyState.uavcan
dronecan/dsdl_specs/com/hex/equipment/flow/20200.Measurement.uavcan
dronecan/dsdl_specs/com/himark/servo/2018.ServoCmd.uavcan
dronecan/dsdl_specs/com/himark/servo/2019.ServoInfo.uavcan
dronecan/dsdl_specs/com/hobbywing/esc/20013.GetEscID.uavcan
dronecan/dsdl_specs/com/hobbywing/esc/20050.StatusMsg1.uavcan
dronecan/dsdl_specs/com/hobbywing/esc/20051.StatusMsg2.uavcan
dronecan/dsdl_specs/com/hobbywing/esc/20052.StatusMsg3.uavcan
dronecan-1.0.25.dist-info/LICENSE
dronecan-1.0.25.dist-info/METADATA
dronecan-1.0.25.dist-info/WHEEL
dronecan-1.0.25.dist-info/top_level.txt
dronecan-1.0.25.dist-info/RECORD
