Metadata-Version: 2.1
Name: dronecan
Version: 1.0.25
Summary: Python implementation of the DroneCAN protocol stack
Home-page: https://dronecan.github.io
Author: Pavel Kirienko, Ben Dyer
Author-email: uavcan@googlegroups.com
License: MIT
Classifier: Development Status :: 3 - Alpha
Classifier: Intended Audience :: Developers
Classifier: Topic :: Software Development :: Libraries
Classifier: License :: OSI Approved :: MIT License
Classifier: Programming Language :: Python
License-File: LICENSE
